one_neuron/__init__.py
one_neuron/all_utils.py
one_neuron/perceptron.py
PERCEPTRON_NAV_NAVANEETHELITE-0.0.1.dist-info/METADATA
PERCEPTRON_NAV_NAVANEETHELITE-0.0.1.dist-info/WHEEL
PERCEPTRON_NAV_NAVANEETHELITE-0.0.1.dist-info/top_level.txt
PERCEPTRON_NAV_NAVANEETHELITE-0.0.1.dist-info/RECORD
